iris_sdk/__init__.py
iris_sdk/constants.py
iris_sdk/context.py
iris_sdk/cost_table.py
iris_sdk/decorators.py
iris_sdk/enums.py
iris_sdk/sdk_client.py
iris_sdk/shared_dataclasses.py
iris_sdk/task.py
iris_sdk/task_context.py
iris_sdk/workflow.py
iris_sdk/langchain/callback_handler.py
iris_sdk-0.1.19.dist-info/licenses/LICENSE
iris_sdk-0.1.19.dist-info/METADATA
iris_sdk-0.1.19.dist-info/WHEEL
iris_sdk-0.1.19.dist-info/top_level.txt
iris_sdk-0.1.19.dist-info/RECORD
