Metadata-Version: 2.4
Name: iris_sdk
Version: 0.1.19
Summary: SDK for Agentic AI workflow management with Iris
Author: Iris
License: Nobody can use this
Requires-Python: >=3.9
License-File: LICENSE
Requires-Dist: openai
Requires-Dist: anthropic
Requires-Dist: google-generativeai
Requires-Dist: langchain-core
Requires-Dist: python-dotenv
Dynamic: license-file
